human_detection/__init__.py
human_detection/command_line.py
human_detection/sec_cam.py
human_detection-0.51.dist-info/LICENSE
human_detection-0.51.dist-info/METADATA
human_detection-0.51.dist-info/WHEEL
human_detection-0.51.dist-info/entry_points.txt
human_detection-0.51.dist-info/top_level.txt
human_detection-0.51.dist-info/RECORD
