Metadata-Version: 2.1
Name: human-detection
Version: 0.51
Summary: set usb camera as security camera, trigger or human detection and send detection video over mail
Home-page: https://github.com/lisrael1/human_detection
Author: Lior Israeli
Author-email: israelilior@gmail.com
License: UNKNOWN
Project-URL: Bug Tracker, https://github.com/lisrael1/human_detection/issues
Platform: UNKNOWN
Classifier: Programming Language :: Python :: 3
Classifier: License :: OSI Approved :: MIT License
Classifier: Operating System :: OS Independent
Requires-Python: >=3.6
License-File: LICENSE
Requires-Dist: dynaconf
Requires-Dist: yagmail
Requires-Dist: opencv-python
Requires-Dist: matplotlib
